paper_qa_pymupdf-2026.1.5.dist-info/licenses/LICENSE
paperqa_pymupdf/__init__.py
paperqa_pymupdf/py.typed
paperqa_pymupdf/reader.py
paperqa_pymupdf/version.py
paper_qa_pymupdf-2026.1.5.dist-info/METADATA
paper_qa_pymupdf-2026.1.5.dist-info/WHEEL
paper_qa_pymupdf-2026.1.5.dist-info/top_level.txt
paper_qa_pymupdf-2026.1.5.dist-info/RECORD
